pydantic_schema_sync-0.1.5.dist-info/METADATA
pydantic_schema_sync-0.1.5.dist-info/WHEEL
pydantic_schema_sync-0.1.5.dist-info/entry_points.txt
pydantic_schema_sync/__init__.py
pydantic_schema_sync/cli.py
pydantic_schema_sync/sync.py
pydantic_schema_sync-0.1.5.dist-info/RECORD
