Metadata-Version: 2.1
Name: pydantic-schema-sync
Version: 0.1.5
Summary: Synchronise Pydantic model schemas with JSONSchema files
Author-Email: Louis Maddox <louismmx@gmail.com>
License: MIT
Project-URL: Homepage, https://github.com/lmmx/pydantic-schema-sync
Project-URL: Repository, https://github.com/lmmx/pydantic-schema-sync.git
Requires-Python: >=3.10
Requires-Dist: pydantic>=2
